paf_tools/__init__.py
paf_tools/configuration.py
paf_tools/data_time.py
paf_tools/database.py
paf_tools/email.py
paf_tools/filesystem.py
paf_tools/generators/address.py
paf_tools/generators/data/addresses/albstadt.py
paf_tools/generators/data/addresses/aschaffenburg.py
paf_tools/generators/data/addresses/augsburg.py
paf_tools/generators/data/addresses/baunatal.py
paf_tools/generators/data/addresses/berlin.py
paf_tools/generators/data/addresses/bielefeld.py
paf_tools/generators/data/addresses/bremen.py
paf_tools/generators/data/addresses/bremerhaven.py
paf_tools/generators/data/addresses/cities.py
paf_tools/generators/data/addresses/detmold.py
paf_tools/generators/data/addresses/frankfurt.py
paf_tools/generators/data/addresses/fulda.py
paf_tools/generators/data/addresses/goslar.py
paf_tools/generators/data/addresses/göttingen.py
paf_tools/generators/data/addresses/halberstadt.py
paf_tools/generators/data/addresses/hamburg.py
paf_tools/generators/data/addresses/hameln.py
paf_tools/generators/data/addresses/hannover.py
paf_tools/generators/data/addresses/kassel.py
paf_tools/generators/data/addresses/kempten.py
paf_tools/generators/data/addresses/münchen.py
paf_tools/generators/data/addresses/norderstedt.py
paf_tools/generators/data/addresses/offenburg.py
paf_tools/generators/data/addresses/parchim.py
paf_tools/generators/data/addresses/rosenheim.py
paf_tools/generators/data/addresses/schweinfurt.py
paf_tools/generators/data/addresses/schwerin.py
paf_tools/generators/data/addresses/stuttgart.py
paf_tools/generators/data/addresses/wolfsburg.py
paf_tools/generators/data/addresses/würzburg.py
paf_tools/generators/data/email/providers.py
paf_tools/generators/data/names/firstnames_female.py
paf_tools/generators/data/names/firstnames_male.py
paf_tools/generators/data/names/genders.py
paf_tools/generators/data/names/lastnames.py
paf_tools/generators/email.py
paf_tools/generators/generators.py
paf_tools/generators/name.py
paf_tools/generators/phone.py
paf_tools-1.0.0.dist-info/WHEEL
paf_tools-1.0.0.dist-info/METADATA
paf_tools-1.0.0.dist-info/RECORD
