Metadata-Version: 2.1
Name: paf-tools
Version: 1.0.0
Summary: 
Author: Your Name
Author-email: you@example.com
Requires-Python: >=3.10,<4.0
Classifier: Programming Language :: Python :: 3
Classifier: Programming Language :: Python :: 3.10
Requires-Dist: PyYAML (>=6.0,<7.0)
Requires-Dist: pymssql (>=2.2.5,<3.0.0)
Requires-Dist: xmltodict (>=0.13.0,<0.14.0)
